docs/run_live_docs_server.py
docs/source/conf.py
metric_forge/__init__.py
metric_forge/ecommerce/__init__.py
metric_forge/ecommerce/polars_ext.py
metric_forge/ecommerce/single_value_functions.py
metric_forge/finance/__init__.py
metric_forge/finance/io.py
metric_forge/finance/objects.py
metric_forge/finance/polars_ext.py
metric_forge/finance/single_value_functions.py
metric_forge/human_capital/__init__.py
metric_forge/human_capital/polars_ext.py
metric_forge/mortgage/__init__.py
metric_forge/mortgage/objects.py
metric_forge/operations/__init__.py
metric_forge/operations/polars_ext.py
metric_forge/product_development/__init__.py
metric_forge/product_development/polars_ext.py
metric_forge/product_development/single_value_functions.py
metric_forge/web_traffic/__init__.py
metric_forge/web_traffic/polars_ext.py
metric_forge/web_traffic/single_value_functions.py
metric_forge-0.4.1.dist-info/LICENSE
metric_forge-0.4.1.dist-info/METADATA
metric_forge-0.4.1.dist-info/WHEEL
metric_forge-0.4.1.dist-info/top_level.txt
metric_forge-0.4.1.dist-info/RECORD
