Metadata-Version: 2.1
Name: metric-forge
Version: 0.4.1
Summary: The Ultimate Metric Library
Author-email: Jayden Rasband <jayden.rasband@gmail.com>
License: MIT
Project-URL: Documentation, https://docs.metric-forge.com
Project-URL: Source, https://github.com/jrasband-dev/metric-forge
Project-URL: Changelog, https://github.com/jrasband-dev/metric-forge/releases
Project-URL: Tracker, https://github.com/jrasband-dev/metric-forge/issues
Project-URL: Contributors, https://github.com/jrasband-dev/metric-forge/graphs/contributors
Project-URL: Repository Stats, https://github.com/jrasband-dev/metric-forge/pulse
Project-URL: Download Stats, https://pypistats.org/packages/metric-forge
License-File: LICENSE
Requires-Dist: polars
Requires-Dist: yfinance
